{"stat.walkOneCm":55768,"stat.leaveGame":2,"stat.useItem.minecraft.diamond_sword":14,"stat.jump":63,"stat.swimOneCm":20687,"stat.fallOneCm":211,"stat.crouchOneCm":230,"stat.sprintOneCm":8932,"stat.useItem.minecraft.mob_spawner":51,"achievement.exploreAllBiomes":{"value":0,"progress":["Forest","Plains"]},"stat.mineBlock.minecraft.lapis_ore":247,"achievement.openInventory":49,"stat.useItem.minecraft.diamond_pickaxe":247,"stat.killEntity.Enderman":1,"stat.mobKills":12,"stat.flyOneCm":35613,"stat.useItem.minecraft.ender_pearl":1,"stat.drop":1,"stat.playOneMinute":18125,"stat.damageDealt":4630,"stat.timeSinceDeath":18125,"stat.killEntity.Cow":10}