{"stat.walkOneCm":704368,"stat.craftItem.minecraft.sign":18,"stat.useItem.minecraft.chest":26,"stat.leaveGame":2,"stat.useItem.minecraft.lava_bucket":4,"stat.useItem.minecraft.diamond_sword":651,"stat.jump":762,"stat.swimOneCm":1286,"stat.fallOneCm":21292,"stat.crouchOneCm":12413,"stat.craftItem.minecraft.chest":27,"stat.useItem.minecraft.stained_hardened_clay":109,"stat.useItem.minecraft.dirt":12,"stat.mineBlock.minecraft.stained_hardened_clay":2,"stat.sprintOneCm":293544,"stat.useItem.minecraft.diamond_shovel":397,"stat.useItem.minecraft.mob_spawner":143,"achievement.exploreAllBiomes":{"value":0,"progress":["Forest","Plains","Desert","The End","Hell"]},"stat.craftItem.minecraft.stick":8,"stat.useItem.minecraft.prismarine":6,"stat.mineBlock.minecraft.lapis_ore":704,"stat.craftItem.minecraft.bucket":4,"achievement.openInventory":78,"stat.craftItem.minecraft.planks":256,"stat.useItem.minecraft.diamond_pickaxe":818,"stat.mobKills":159,"stat.useItem.minecraft.bucket":4,"stat.flyOneCm":354653,"stat.drop":41,"stat.playOneMinute":101283,"stat.damageDealt":205978,"stat.timeSinceDeath":101283,"stat.mineBlock.minecraft.dirt":455,"stat.useItem.minecraft.sign":54}