{"stat.flyOneCm":46516,"stat.walkOneCm":68477,"stat.drop":2,"stat.jump":226,"stat.swimOneCm":30,"stat.playOneMinute":14089,"stat.fallOneCm":5538,"achievement.openInventory":9,"stat.climbOneCm":948,"stat.mineBlock.minecraft.diamond_ore":164,"stat.leaveGame":1,"stat.damageDealt":30,"stat.crouchOneCm":1196,"stat.useItem.minecraft.diamond_pickaxe":364,"stat.timeSinceDeath":14089,"stat.sprintOneCm":26682,"achievement.exploreAllBiomes":{"value":0,"progress":["Plains"]},"stat.mineBlock.minecraft.emerald_ore":200}