{"stat.walkOneCm":42450,"stat.mineBlock.minecraft.lapis_ore":89,"stat.craftItem.minecraft.sign":3,"stat.useItem.minecraft.chest":1,"achievement.openInventory":16,"stat.craftItem.minecraft.planks":256,"stat.leaveGame":1,"stat.craftItem.minecraft.crafting_table":1,"stat.useItem.minecraft.diamond_pickaxe":89,"stat.useItem.minecraft.diamond_sword":1,"stat.flyOneCm":16614,"stat.mineBlock.minecraft.planks":1,"stat.jump":68,"stat.playOneMinute":12620,"stat.fallOneCm":1635,"stat.useItem.minecraft.planks":1,"achievement.buildWorkBench":2,"stat.crouchOneCm":292,"stat.timeSinceDeath":12620,"achievement.mineWood":2,"stat.craftItem.minecraft.chest":1,"stat.sprintOneCm":24180,"stat.useItem.minecraft.crafting_table":1,"stat.useItem.minecraft.sign":5,"stat.mineBlock.minecraft.dirt":1,"achievement.exploreAllBiomes":{"value":0,"progress":["Forest","Plains"]},"stat.craftItem.minecraft.stick":4}