{"stat.walkOneCm":251482,"stat.craftItem.minecraft.lapis_block":1,"stat.mineBlock.minecraft.lapis_ore":4219,"stat.useItem.minecraft.chest":8,"achievement.openInventory":102,"stat.craftItem.minecraft.planks":256,"stat.leaveGame":2,"stat.craftItem.minecraft.crafting_table":1,"stat.useItem.minecraft.diamond_pickaxe":4226,"stat.flyOneCm":82477,"stat.drop":6,"stat.jump":362,"stat.playOneMinute":42339,"stat.fallOneCm":9010,"stat.crouchOneCm":7845,"stat.timeSinceDeath":42339,"stat.craftItem.minecraft.chest":8,"stat.sprintOneCm":137125,"stat.useItem.minecraft.crafting_table":1,"stat.mineBlock.minecraft.dirt":18,"achievement.exploreAllBiomes":{"value":0,"progress":["Forest","Plains"]}}