{"stat.flyOneCm":103791,"stat.walkOneCm":142932,"stat.drop":3,"stat.jump":229,"stat.useItem.minecraft.quartz_block":233,"stat.mineBlock.minecraft.lapis_ore":2280,"stat.useItem.minecraft.snow":222,"stat.playOneMinute":36329,"stat.fallOneCm":4822,"achievement.openInventory":23,"stat.leaveGame":2,"stat.crouchOneCm":20728,"stat.useItem.minecraft.diamond_pickaxe":2307,"stat.mineBlock.minecraft.quartz_block":27,"stat.timeSinceDeath":36329,"stat.useItem.minecraft.dirt":6,"stat.sprintOneCm":36366,"stat.useItem.minecraft.diamond_shovel":349,"stat.mineBlock.minecraft.dirt":351,"achievement.exploreAllBiomes":{"value":0,"progress":["Forest","Plains"]}}