{"stat.useItem.minecraft.quartz_block":1205,"stat.craftItem.minecraft.sign":57,"stat.craftItem.minecraft.ladder":6,"stat.leaveGame":7,"stat.useItem.minecraft.beacon":15,"stat.useItem.minecraft.diamond_axe":399,"stat.useItem.minecraft.diamond_sword":1837,"stat.useItem.minecraft.quartz_ore":1,"stat.mineBlock.minecraft.stained_glass":18,"stat.jump":2939,"stat.swimOneCm":67110,"stat.fallOneCm":44999,"stat.climbOneCm":3007,"stat.crouchOneCm":133685,"stat.mineBlock.minecraft.chest":6,"stat.useItem.minecraft.dirt":59,"stat.useItem.minecraft.mob_spawner":112,"achievement.exploreAllBiomes":{"value":0,"progress":["Forest","Plains"]},"stat.useItem.minecraft.water_bucket":25,"stat.useItem.minecraft.red_flower":16,"stat.mineBlock.minecraft.lapis_ore":1762,"stat.mineBlock.minecraft.red_flower":16,"stat.mineBlock.minecraft.obsidian":2,"stat.flyOneCm":1272467,"stat.damageDealt":797804,"stat.timeSinceDeath":482968,"stat.killEntity.Cow":1,"stat.useItem.minecraft.sign":93,"stat.useItem.minecraft.crafting_table":1,"stat.mineBlock.minecraft.dirt":651,"stat.craftItem.minecraft.stone_slab":18,"stat.walkOneCm":1923617,"stat.useItem.minecraft.chest":16,"stat.craftItem.minecraft.crafting_table":1,"stat.useItem.minecraft.lava_bucket":17,"stat.mineBlock.minecraft.emerald_ore":255,"stat.useItem.minecraft.stained_glass":86,"stat.sprintOneCm":851714,"stat.useItem.minecraft.diamond_shovel":568,"stat.mineBlock.minecraft.stone_slab":24,"stat.craftItem.minecraft.stick":128,"stat.useItem.minecraft.prismarine":4,"stat.useItem.minecraft.stone_slab":30,"achievement.openInventory":315,"stat.craftItem.minecraft.planks":512,"stat.mineBlock.minecraft.diamond_ore":263,"stat.useItem.minecraft.diamond_pickaxe":2988,"stat.mineBlock.minecraft.quartz_block":527,"stat.mobKills":760,"stat.craftItem.minecraft.wooden_pressure_plate":1,"stat.useItem.minecraft.bucket":23,"stat.useItem.minecraft.golden_apple":1,"stat.drop":196,"stat.playOneMinute":482968,"stat.useItem.minecraft.ladder":5,"stat.mineBlock.minecraft.stone":42,"stat.diveOneCm":486}