{"stat.useItem.minecraft.quartz_block":2420,"stat.useItem.minecraft.stone":92,"stat.craftItem.minecraft.carpet":384,"stat.useItem.minecraft.quartz_stairs":88,"stat.leaveGame":11,"stat.useItem.minecraft.beacon":12,"stat.craftItem.minecraft.quartz_stairs":84,"stat.useItem.minecraft.diamond_sword":82,"stat.useItem.minecraft.carpet":383,"stat.useItem.minecraft.stained_glass_pane":191,"stat.useItem.minecraft.glowstone":34,"stat.mineBlock.minecraft.stained_glass_pane":16,"stat.mineBlock.minecraft.stained_glass":2,"stat.jump":2139,"stat.swimOneCm":1492,"stat.fallOneCm":80402,"stat.useItem.minecraft.planks":94,"stat.useItem.minecraft.nether_brick_stairs":5,"stat.crouchOneCm":17354,"stat.craftItem.minecraft.chest":4,"achievement.exploreAllBiomes":{"value":0,"progress":["Jungle","Forest","Plains"]},"stat.mineBlock.minecraft.carpet":2,"stat.flyOneCm":2510557,"stat.damageDealt":32306,"stat.useItem.minecraft.wool":1,"stat.timeSinceDeath":539610,"stat.mineBlock.minecraft.nether_brick_stairs":1,"stat.useItem.minecraft.crafting_table":1,"stat.craftItem.minecraft.stone_slab":1750,"stat.mineBlock.minecraft.quartz_stairs":16,"stat.walkOneCm":825678,"stat.useItem.minecraft.chest":4,"stat.mineBlock.minecraft.wool":1,"stat.useItem.minecraft.stained_hardened_clay":760,"stat.mineBlock.minecraft.stained_hardened_clay":60,"stat.sprintOneCm":374145,"stat.useItem.minecraft.stained_glass":8,"stat.mineBlock.minecraft.stone_slab":83,"stat.useItem.minecraft.stone_slab":1397,"stat.craftItem.minecraft.stained_glass_pane":448,"achievement.openInventory":277,"stat.mineBlock.minecraft.stonebrick":3,"stat.craftItem.minecraft.planks":784,"stat.useItem.minecraft.diamond_pickaxe":578,"stat.mineBlock.minecraft.quartz_block":397,"stat.mobKills":25,"stat.useItem.minecraft.stonebrick":90,"stat.craftItem.minecraft.wooden_door":6,"stat.useItem.minecraft.dye":64,"stat.useItem.minecraft.wooden_door":5,"stat.useItem.minecraft.golden_apple":2,"stat.mineBlock.minecraft.planks":2,"stat.drop":23,"stat.playOneMinute":539610,"stat.craftItem.minecraft.nether_brick_stairs":64,"stat.mineBlock.minecraft.stone":13,"stat.mineBlock.minecraft.tallgrass":1}