{"stat.leaveGame":6,"stat.killEntity.Slime":1,"stat.useItem.minecraft.beacon":2,"stat.useItem.minecraft.diamond_sword":244,"stat.mineBlock.minecraft.stained_glass":28,"stat.jump":1783,"stat.swimOneCm":5026,"stat.fallOneCm":33878,"stat.crouchOneCm":59935,"stat.craftItem.minecraft.iron_ingot":1440,"stat.craftItem.minecraft.chest":7,"stat.useItem.minecraft.mob_spawner":19,"achievement.exploreAllBiomes":{"value":0,"progress":["Forest","Plains"]},"stat.mineBlock.minecraft.lapis_ore":2131,"stat.flyOneCm":546756,"stat.damageDealt":59114,"stat.killEntity.Rabbit":15,"stat.timeSinceDeath":158314,"stat.useItem.minecraft.crafting_table":1,"stat.mineBlock.minecraft.dirt":2,"stat.walkOneCm":875274,"stat.useItem.minecraft.chest":2,"stat.craftItem.minecraft.crafting_table":1,"stat.mineBlock.minecraft.packed_ice":8,"stat.mineBlock.minecraft.stained_hardened_clay":11,"stat.sprintOneCm":322645,"stat.useItem.minecraft.cactus":1,"stat.useItem.minecraft.fence":29,"stat.craftItem.minecraft.stick":64,"stat.craftItem.minecraft.wooden_axe":1,"stat.mineBlock.minecraft.cactus":1,"achievement.openInventory":199,"stat.craftItem.minecraft.planks":256,"stat.mineBlock.minecraft.fence":4,"stat.mineBlock.minecraft.prismarine":45,"stat.useItem.minecraft.diamond_pickaxe":2227,"stat.mobKills":59,"stat.craftItem.minecraft.fence":48,"stat.drop":39,"stat.playOneMinute":158314,"stat.killEntity.Zombie":1,"stat.useItem.minecraft.wooden_axe":4,"stat.diveOneCm":262}