{"stat.useItem.minecraft.golden_apple":1,"stat.flyOneCm":4213,"stat.deaths":1,"stat.walkOneCm":62765,"stat.jump":38,"stat.mineBlock.minecraft.lapis_ore":984,"stat.playOneMinute":9516,"achievement.openInventory":7,"stat.fallOneCm":1686,"stat.mineBlock.minecraft.diamond_ore":260,"stat.leaveGame":1,"stat.useItem.minecraft.diamond_pickaxe":1490,"stat.crouchOneCm":390,"stat.timeSinceDeath":1089,"stat.sprintOneCm":25582,"achievement.exploreAllBiomes":{"value":0,"progress":["Plains"]},"stat.mineBlock.minecraft.emerald_ore":246}